{
  "generator-jhipster": {
    "promptValues": {
      "packageName": "com.timiris.crm",
      "nativeLanguage": "fr"
    },
    "jhipsterVersion": "4.5.6",
    "baseName": "timirisCrm",
    "packageName": "com.timiris.crm",
    "packageFolder": "com/timiris/crm",
    "serverPort": "8080",
    "authenticationType": "session",
    "hibernateCache": "ehcache",
    "clusteredHttpSession": false,
    "websocket": false,
    "databaseType": "sql",
    "devDatabaseType": "h2Memory",
    "prodDatabaseType": "postgresql",
    "searchEngine": false,
    "messageBroker": false,
    "serviceDiscoveryType": false,
    "buildTool": "maven",
    "enableSocialSignIn": false,
    "rememberMeKey": "76ab51db5c693381bbc4f736e520d27f00b299a7",
    "clientFramework": "angular2",
    "useSass": true,
    "clientPackageManager": "yarn",
    "applicationType": "monolith",
    "testFrameworks": [],
    "jhiPrefix": "jhi",
    "enableTranslation": true,
    "nativeLanguage": "fr",
    "languages": [
      "fr"
    ]
  }
}